csv_db_package/__init__.py
csv_db_package/create_db.py
csv_db_package/crud_operations.py
csv_db_package/fileserver.py
csv_db_package/Templates/add_data.html
csv_db_package/Templates/index.html
csv_db_package/Templates/update_data.html
csv_db_package/Templates/upload_file.html
csv_db_package/Templates/view_table.html
csv_db_package-0.0.3.dist-info/LICENSE
csv_db_package-0.0.3.dist-info/METADATA
csv_db_package-0.0.3.dist-info/WHEEL
csv_db_package-0.0.3.dist-info/top_level.txt
csv_db_package-0.0.3.dist-info/RECORD
