Metadata-Version: 2.1
Name: csv_db_package
Version: 0.0.3
Summary: This package is found useful for those who wants to modify their CSV file without using database.It creates a local server that having a functionality of uploading a csv file and then perform crud operations through browser itself.
Home-page: https://github.com/ankitaliya/csv_db_package
Author: Ankita Liya
Author-email: ankitaliya321@gmail.com
License: UNKNOWN
Project-URL: Bug Tracker, https://github.com/ankitaliya/csv_db_package/issues
Platform: UNKNOWN
Classifier: Programming Language :: Python :: 3
Classifier: License :: OSI Approved :: MIT License
Classifier: Operating System :: OS Independent
Requires-Python: >=3.7
License-File: LICENSE
